VHDL/UDP_RGMII_stack/src/MAC_RX.vhd
library ieee;
use ieee.std_logic_1164.all;
use ieee.numeric_std.all;

entity mac_rx is
port (
    clk         : in  std_logic;
    reset       : in  std_logic;

    --------------------------------------------------------------------
    -- GMII INPUT
    --------------------------------------------------------------------
    gmii_rxd    : in  std_logic_vector(7 downto 0);
    gmii_rx_dv  : in  std_logic;
    gmii_rx_er  : in  std_logic;

    --------------------------------------------------------------------
    -- AXI STREAM OUTPUT
    --------------------------------------------------------------------
    m_data      : out std_logic_vector(7 downto 0);
    m_valid     : out std_logic;
    m_last      : out std_logic;
    m_ready     : in  std_logic
);
end entity;

architecture rtl of mac_rx is

    --------------------------------------------------------------------
    -- FSM
    --------------------------------------------------------------------
    type state_t is (
        IDLE,
        PREAMBLE,
        PAYLOAD,
        DROP
    );

    signal state      : state_t := IDLE;
    signal next_state : state_t := IDLE;

    --------------------------------------------------------------------
    -- REGISTERS
    --------------------------------------------------------------------
    signal pre_cnt        : integer range 0 to 7 := 0;
    signal next_pre_cnt   : integer range 0 to 7 := 0;

    signal rx_data_reg    : std_logic_vector(7 downto 0) := (others => '0');
    signal rx_valid_reg   : std_logic := '0';
    signal rx_last_reg    : std_logic := '0';

    signal next_data      : std_logic_vector(7 downto 0);
    signal next_valid     : std_logic;
    signal next_last      : std_logic;

    signal dv_d      : std_logic;
    signal data_d    : std_logic_vector(7 downto 0);

begin

    --------------------------------------------------------------------
    -- OUTPUTS
    --------------------------------------------------------------------
    m_valid <= rx_valid_reg;
    m_data  <= data_d;
    m_last  <= dv_d and not gmii_rx_dv;

    --------------------------------------------------------------------
    -- CLOCKED PROCESS
    --------------------------------------------------------------------
    process(clk)
    begin
        if rising_edge(clk) then

            if reset = '1' then

                state        <= IDLE;
                pre_cnt      <= 0;

                rx_data_reg  <= (others => '0');
                rx_valid_reg <= '0';
                rx_last_reg  <= '0';

                dv_d   <= '0';
                data_d <= (others => '0');

            else

                ----------------------------------------------------------------
                -- REGISTER UPDATE
                ----------------------------------------------------------------
                state        <= next_state;
                pre_cnt      <= next_pre_cnt;

                rx_data_reg  <= next_data;
                rx_valid_reg <= next_valid;
                rx_last_reg  <= next_last;


                dv_d   <= gmii_rx_dv;
                data_d <= gmii_rxd;

            end if;
        end if;
    end process;

    --------------------------------------------------------------------
    -- FSM / COMBINATORIAL
    --------------------------------------------------------------------
    process(all)
    begin

        ----------------------------------------------------------------
        -- DEFAULTS
        ----------------------------------------------------------------
        next_state    <= state;
        next_pre_cnt  <= pre_cnt;

        next_data     <= rx_data_reg;
        next_valid    <= '0';
        next_last     <= '0';

        case state is

            ----------------------------------------------------------------
            -- IDLE
            ----------------------------------------------------------------
            when IDLE =>
                
                if gmii_rx_dv = '1' then

                    if gmii_rxd = x"55" then

                        next_pre_cnt <= 1;
                        next_state   <= PREAMBLE;

                    else

                        next_state <= DROP;

                    end if;

                end if;

            ----------------------------------------------------------------
            -- PREAMBLE DETECTION
            ----------------------------------------------------------------
            when PREAMBLE =>
                
                if gmii_rx_dv = '1' then

                    --------------------------------------------------------
                    -- PREAMBLE BYTES
                    --------------------------------------------------------
                    if pre_cnt < 7 then

                        if gmii_rxd = x"55" then
                            
                            next_pre_cnt <= pre_cnt + 1;

                        else
                            
                            next_state <= DROP;

                        end if;

                    --------------------------------------------------------
                    -- SFD
                    --------------------------------------------------------
                    else

                        if gmii_rxd = x"D5" then
                            
                            next_state <= PAYLOAD;

                        else
                            
                            next_state <= DROP;

                        end if;

                    end if;

                else

                    next_state <= IDLE;

                end if;

            ----------------------------------------------------------------
            -- PAYLOAD RECEIVE
            ----------------------------------------------------------------
            when PAYLOAD =>
                
                if gmii_rx_er = '1' then

                    next_state <= DROP;

                elsif gmii_rx_dv = '1' then

                    if m_ready = '1' then

                        next_data  <= gmii_rxd;
                        next_valid <= '1';

                    end if;

                else

                    ----------------------------------------------------------------
                    -- END OF FRAME
                    ----------------------------------------------------------------
                    next_last  <= '1';
                    next_state <= IDLE;

                end if;

            ----------------------------------------------------------------
            -- DROP FRAME
            ----------------------------------------------------------------
            when DROP =>
                
                if gmii_rx_dv = '0' then

                    next_state <= IDLE;

                end if;

        end case;

    end process;

end architecture;

VHDL/UDP_RGMII_stack/tb/MAC_RX_tb.vhd
library ieee;
use ieee.std_logic_1164.all;
use ieee.numeric_std.all;

entity mac_rx_tb is
end entity;

architecture sim of mac_rx_tb is

    --------------------------------------------------------------------
    -- CLOCK
    --------------------------------------------------------------------
    constant CLK_PERIOD : time := 8 ns;

    signal clk   : std_logic := '0';
    signal reset : std_logic := '1';

    --------------------------------------------------------------------
    -- GMII RX INPUTS
    --------------------------------------------------------------------
    signal gmii_rxd   : std_logic_vector(7 downto 0) := (others => '0');
    signal gmii_rx_dv : std_logic := '0';
    signal gmii_rx_er : std_logic := '0';

    --------------------------------------------------------------------
    -- AXI OUTPUTS
    --------------------------------------------------------------------
    signal m_data  : std_logic_vector(7 downto 0);
    signal m_valid : std_logic;
    signal m_last  : std_logic;
    signal m_ready : std_logic := '1';

    --------------------------------------------------------------------
    -- COUNTER
    --------------------------------------------------------------------
    signal rx_cnt : integer := 0;

begin

    --------------------------------------------------------------------
    -- DUT
    --------------------------------------------------------------------
    dut : entity work.mac_rx
    port map (
        clk        => clk,
        reset      => reset,

        gmii_rxd   => gmii_rxd,
        gmii_rx_dv => gmii_rx_dv,
        gmii_rx_er => gmii_rx_er,

        m_data     => m_data,
        m_valid    => m_valid,
        m_last     => m_last,
        m_ready    => m_ready
    );

    --------------------------------------------------------------------
    -- CLOCK
    --------------------------------------------------------------------
    clk <= not clk after CLK_PERIOD/2;

    --------------------------------------------------------------------
    -- STIMULUS
    --------------------------------------------------------------------
    stim_proc : process

        ----------------------------------------------------------------
        -- SEND BYTE PROCEDURE
        ----------------------------------------------------------------
        procedure send_byte(data : std_logic_vector(7 downto 0)) is
        begin
            gmii_rxd   <= data;
            gmii_rx_dv <= '1';

            wait until rising_edge(clk);
        end procedure;

    begin

        ----------------------------------------------------------------
        -- RESET
        ----------------------------------------------------------------
        wait for 40 ns;

        reset <= '0';

        wait for 20 ns;

        report "START RX TEST";

        ----------------------------------------------------------------
        -- PREAMBLE
        ----------------------------------------------------------------
        send_byte(x"55");
        send_byte(x"55");
        send_byte(x"55");
        send_byte(x"55");
        send_byte(x"55");
        send_byte(x"55");
        send_byte(x"55");

        ----------------------------------------------------------------
        -- SFD
        ----------------------------------------------------------------
        send_byte(x"D5");

        ----------------------------------------------------------------
        -- PAYLOAD
        ----------------------------------------------------------------
        send_byte(x"11");
        send_byte(x"22");
        send_byte(x"33");
        send_byte(x"44");
        send_byte(x"55");
        send_byte(x"66");
        send_byte(x"77");
        send_byte(x"88");

        ----------------------------------------------------------------
        -- END FRAME
        ----------------------------------------------------------------
        gmii_rx_dv <= '0';

        wait until rising_edge(clk);

        ----------------------------------------------------------------
        -- WAIT
        ----------------------------------------------------------------
        wait for 200 ns;

        assert false
        report "RX TEST COMPLETE"
        severity failure;

    end process;

    --------------------------------------------------------------------
    -- MONITOR OUTPUT
    --------------------------------------------------------------------
    monitor_proc : process(clk)
    begin
        if rising_edge(clk) then

            if m_valid = '1' then

                report
                    "RX[" &
                    integer'image(rx_cnt) &
                    "] = 0x" &
                    to_hstring(m_data);

                rx_cnt <= rx_cnt + 1;

            end if;

            if m_last = '1' then

                report "RX LAST ASSERTED";

            end if;

        end if;
    end process;

end architecture;

VHDL/UDP_RGMII_stack/wave_MAC_RX.vcd
$date
  Wed May 13 07:27:58 2026
$end
$version
  GHDL v0
$end
$timescale
  1 fs
$end
$scope module standard $end
$upscope $end
$scope module textio $end
$upscope $end
$scope module std_logic_1164 $end
$upscope $end
$scope module numeric_std $end
$upscope $end
$scope module mac_rx_tb $end
$var reg 1 ! clk $end
$var reg 1 " reset $end
$var reg 8 # gmii_rxd[7:0] $end
$var reg 1 $ gmii_rx_dv $end
$var reg 1 % gmii_rx_er $end
$var reg 8 & m_data[7:0] $end
$var reg 1 ' m_valid $end
$var reg 1 ( m_last $end
$var reg 1 ) m_ready $end
$var integer 32 * rx_cnt $end
$scope module dut $end
$var reg 1 + clk $end
$var reg 1 , reset $end
$var reg 8 - gmii_rxd[7:0] $end
$var reg 1 . gmii_rx_dv $end
$var reg 1 / gmii_rx_er $end
$var reg 8 0 m_data[7:0] $end
$var reg 1 1 m_valid $end
$var reg 1 2 m_last $end
$var reg 1 3 m_ready $end
$comment state is not handled $end
$comment next_state is not handled $end
$var integer 32 4 pre_cnt $end
$var integer 32 5 next_pre_cnt $end
$var reg 8 6 rx_data_reg[7:0] $end
$var reg 1 7 rx_valid_reg $end
$var reg 1 8 rx_last_reg $end
$var reg 8 9 next_data[7:0] $end
$var reg 1 : next_valid $end
$var reg 1 ; next_last $end
$var reg 1 < dv_d $end
$var reg 8 = data_d[7:0] $end
$upscope $end
$upscope $end
$enddefinitions $end
#0
0!
1"
b00000000 #
0$
0%
bUUUUUUUU &
0'
U(
1)
b0 *
0+
1,
b00000000 -
0.
0/
bUUUUUUUU 0
01
U2
13
b0 4
b0 5
b00000000 6
07
08
b00000000 9
0:
0;
U<
bUUUUUUUU =
#4000000
1!
b00000000 &
0(
1+
b00000000 0
02
0<
b00000000 =
#8000000
0!
0+
#12000000
1!
1+
#16000000
0!
0+
#20000000
1!
1+
#24000000
0!
0+
#28000000
1!
1+
#32000000
0!
0+
#36000000
1!
1+
#40000000
0!
0"
0+
0,
#44000000
1!
1+
#48000000
0!
0+
#52000000
1!
1+
#56000000
0!
0+
#60000000
1!
b01010101 #
1$
1+
b01010101 -
1.
b1 5
#64000000
0!
0+
#68000000
1!
b01010101 &
1+
b01010101 0
b1 4
b10 5
1<
b01010101 =
#72000000
0!
0+
#76000000
1!
1+
b10 4
b11 5
#80000000
0!
0+
#84000000
1!
1+
b11 4
b100 5
#88000000
0!
0+
#92000000
1!
1+
b100 4
b101 5
#96000000
0!
0+
#100000000
1!
1+
b101 4
b110 5
#104000000
0!
0+
#108000000
1!
1+
b110 4
b111 5
#112000000
0!
0+
#116000000
1!
b11010101 #
1+
b11010101 -
b111 4
#120000000
0!
0+
#124000000
1!
b00010001 #
b11010101 &
1+
b00010001 -
b11010101 0
b00010001 9
1:
b11010101 =
#128000000
0!
0+
#132000000
1!
b00100010 #
b00010001 &
1'
1+
b00100010 -
b00010001 0
11
b00010001 6
17
b00100010 9
b00010001 =
#136000000
0!
0+
#140000000
1!
b00110011 #
b00100010 &
b1 *
1+
b00110011 -
b00100010 0
b00100010 6
b00110011 9
b00100010 =
#144000000
0!
0+
#148000000
1!
b01000100 #
b00110011 &
b10 *
1+
b01000100 -
b00110011 0
b00110011 6
b01000100 9
b00110011 =
#152000000
0!
0+
#156000000
1!
b01010101 #
b01000100 &
b11 *
1+
b01010101 -
b01000100 0
b01000100 6
b01010101 9
b01000100 =
#160000000
0!
0+
#164000000
1!
b01100110 #
b01010101 &
b100 *
1+
b01100110 -
b01010101 0
b01010101 6
b01100110 9
b01010101 =
#168000000
0!
0+
#172000000
1!
b01110111 #
b01100110 &
b101 *
1+
b01110111 -
b01100110 0
b01100110 6
b01110111 9
b01100110 =
#176000000
0!
0+
#180000000
1!
b10001000 #
b01110111 &
b110 *
1+
b10001000 -
b01110111 0
b01110111 6
b10001000 9
b01110111 =
#184000000
0!
0+
#188000000
1!
0$
b10001000 &
1(
b111 *
1+
0.
b10001000 0
12
b10001000 6
0:
1;
b10001000 =
#192000000
0!
0+
#196000000
1!
0'
0(
b1000 *
1+
01
02
07
18
0;
0<
#200000000
0!
0+
#204000000
1!
1+
08
