VHDL/UDP_RGMII_stack/src/RGMII.vhd
library ieee;
use ieee.std_logic_1164.all;
use ieee.numeric_std.all;

--
--TX
--

entity rgmii_tx is
port (
    clk125   : in  std_logic;
    reset    : in  std_logic;

    txd_in   : in  std_logic_vector(7 downto 0);
    tx_en    : in  std_logic;
    tx_er    : in  std_logic;

    rgmii_txd  : out std_logic_vector(3 downto 0) := (others => '0');
    rgmii_txctl: out std_logic := '0';
    rgmii_txc  : out std_logic
);
end entity;

architecture rtl of rgmii_tx is
    signal txd_reg : std_logic_vector(7 downto 0) := (others => '0');
    signal ctl_reg : std_logic := '0';
begin

    process(clk125)
    begin
        if rising_edge(clk125) then
            txd_reg <= txd_in;
            ctl_reg <= tx_en xor tx_er;
        end if;
    end process;

    -- DDR transmit (simplified behavioral model)
    process(clk125)
    begin
        if rising_edge(clk125) then
            rgmii_txd   <= txd_reg(3 downto 0); -- low nibble
            rgmii_txctl <= ctl_reg;
        elsif falling_edge(clk125) then
            rgmii_txd   <= txd_reg(7 downto 4); -- high nibble
            rgmii_txctl <= ctl_reg;
        end if;
    end process;

    rgmii_txc <= clk125;

end architecture;


library ieee;
use ieee.std_logic_1164.all;
use ieee.numeric_std.all;

--
--RX
--
entity rgmii_rx is
port (
    rx_clk   : in  std_logic;
    reset    : in  std_logic;

    rgmii_rxd   : in  std_logic_vector(3 downto 0);
    rgmii_rxctl : in  std_logic;

    rx_dout  : out std_logic_vector(7 downto 0);
    rx_dv    : out std_logic;
    rx_er    : out std_logic
);
end entity;

architecture rtl of rgmii_rx is
    signal low_nibble  : std_logic_vector(3 downto 0);
    signal high_nibble : std_logic_vector(3 downto 0);
    signal ctl_rise, ctl_fall, next_dv, next_er : std_logic;
    signal next_rx_dout : std_logic_vector(7 downto 0);
begin

    process(rx_clk, high_nibble, ctl_fall)
    begin
        if rising_edge(rx_clk) then
            low_nibble <= rgmii_rxd;
            ctl_rise   <= rgmii_rxctl;
            
            next_rx_dout <= high_nibble & rgmii_rxd;
            next_dv <= rgmii_rxctl;
            next_er <= rgmii_rxctl xor ctl_fall;
        elsif falling_edge(rx_clk) then
            high_nibble <= rgmii_rxd;
            ctl_fall    <= rgmii_rxctl;
        end if;
    end process;

    process(rx_clk, next_rx_dout, ctl_rise, ctl_fall)
    begin
        if rising_edge(rx_clk) then
            rx_dout <= next_rx_dout;

            rx_dv <= next_dv;
            rx_er <= next_er;
        end if;
    end process;

end architecture;

VHDL/UDP_RGMII_stack/tb/RGMII_tb.vhd
library ieee;
use ieee.std_logic_1164.all;
use ieee.numeric_std.all;

entity rgmii_tb is
end entity;

architecture sim of rgmii_tb is

    -- DUT signals
    signal clk125 : std_logic := '0';
    signal reset  : std_logic := '1';
    signal rx_clk : std_logic := '0';

    -- TX signals
    signal txd_in   : std_logic_vector(7 downto 0) := (others => '0');
    signal tx_en    : std_logic := '0';
    signal tx_er    : std_logic := '0';
    signal rgmii_txd   : std_logic_vector(3 downto 0);
    signal rgmii_txctl : std_logic;
    signal rgmii_txc   : std_logic;

    -- RX signals (loopback)
    signal rgmii_rxd   : std_logic_vector(3 downto 0);
    signal rgmii_rxctl : std_logic;
    signal rx_dout  : std_logic_vector(7 downto 0);
    signal rx_dv    : std_logic;
    signal rx_er    : std_logic;

    -- clock period (125 MHz = 8 ns)
    constant clk_period : time := 8 ns;

begin

    ------------------------------------------------------------
    -- Clock generation
    ------------------------------------------------------------
    clk_process : process
    begin
        while true loop
            clk125 <= '0';
            wait for clk_period/2;
            clk125 <= '1';
            wait for clk_period/2;
        end loop;
    end process;

    -- 2 ns delayed RX clock
    rx_clk <= transport clk125 after 2 ns;

    ------------------------------------------------------------
    -- Instantiate TX DUT
    ------------------------------------------------------------
    tx_inst : entity work.rgmii_tx
    port map (
        clk125       => clk125,
        reset        => reset,
        txd_in       => txd_in,
        tx_en        => tx_en,
        tx_er        => tx_er,
        rgmii_txd    => rgmii_txd,
        rgmii_txctl  => rgmii_txctl,
        rgmii_txc    => rgmii_txc
    );

    ------------------------------------------------------------
    -- Loopback model (TX → RX wiring simulation)
    ------------------------------------------------------------
    rgmii_rxd   <= transport rgmii_txd after 500 ps;
    rgmii_rxctl <= transport rgmii_txctl after 500 ps;

    ------------------------------------------------------------
    -- Instantiate RX DUT
    ------------------------------------------------------------
    rx_inst : entity work.rgmii_rx
    port map (
        rx_clk       => rx_clk,
        reset        => reset,
        rgmii_rxd    => rgmii_rxd,
        rgmii_rxctl  => rgmii_rxctl,
        rx_dout      => rx_dout,
        rx_dv        => rx_dv,
        rx_er        => rx_er
    );

    ------------------------------------------------------------
    -- Stimulus process
    ------------------------------------------------------------
    stim_proc : process
    begin
        -- reset
        reset <= '1';
        wait for 20 ns;
        reset <= '0';

        --------------------------------------------------------
        -- Send a few Ethernet-like bytes
        --------------------------------------------------------
        tx_en <= '1';

        txd_in <= x"AB";
        wait for clk_period;

        txd_in <= x"56";
        wait for clk_period;

        txd_in <= x"EF";
        wait for clk_period;

        txd_in <= x"98";
        wait for clk_period;

        tx_en <= '0';

        wait for 100 ns;

        --------------------------------------------------------
        -- End simulation
        --------------------------------------------------------
        assert false report "Simulation finished" severity failure;

    end process;

end architecture;

VHDL/UDP_RGMII_stack/wave_rgmii.vcd
$date
  Wed May 13 08:17:15 2026
$end
$version
  GHDL v0
$end
$timescale
  1 fs
$end
$scope module standard $end
$upscope $end
$scope module textio $end
$upscope $end
$scope module std_logic_1164 $end
$upscope $end
$scope module numeric_std $end
$upscope $end
$scope module rgmii_tb $end
$var reg 1 ! clk125 $end
$var reg 1 " reset $end
$var reg 1 # rx_clk $end
$var reg 8 $ txd_in[7:0] $end
$var reg 1 % tx_en $end
$var reg 1 & tx_er $end
$var reg 4 ' rgmii_txd[3:0] $end
$var reg 1 ( rgmii_txctl $end
$var reg 1 ) rgmii_txc $end
$var reg 4 * rgmii_rxd[3:0] $end
$var reg 1 + rgmii_rxctl $end
$var reg 8 , rx_dout[7:0] $end
$var reg 1 - rx_dv $end
$var reg 1 . rx_er $end
$scope module tx_inst $end
$var reg 1 / clk125 $end
$var reg 1 0 reset $end
$var reg 8 1 txd_in[7:0] $end
$var reg 1 2 tx_en $end
$var reg 1 3 tx_er $end
$var reg 4 4 rgmii_txd[3:0] $end
$var reg 1 5 rgmii_txctl $end
$var reg 1 6 rgmii_txc $end
$var reg 8 7 txd_reg[7:0] $end
$var reg 1 8 ctl_reg $end
$upscope $end
$scope module rx_inst $end
$var reg 1 9 rx_clk $end
$var reg 1 : reset $end
$var reg 4 ; rgmii_rxd[3:0] $end
$var reg 1 < rgmii_rxctl $end
$var reg 8 = rx_dout[7:0] $end
$var reg 1 > rx_dv $end
$var reg 1 ? rx_er $end
$var reg 4 @ low_nibble[3:0] $end
$var reg 4 A high_nibble[3:0] $end
$var reg 1 B ctl_rise $end
$var reg 1 C ctl_fall $end
$var reg 1 D next_dv $end
$var reg 1 E next_er $end
$var reg 8 F next_rx_dout[7:0] $end
$upscope $end
$upscope $end
$enddefinitions $end
#0
0!
1"
0#
b00000000 $
0%
0&
b0000 '
0(
0)
bUUUU *
U+
bUUUUUUUU ,
U-
U.
0/
10
b00000000 1
02
03
b0000 4
05
06
b00000000 7
08
09
1:
bUUUU ;
U<
bUUUUUUUU =
U>
U?
bUUUU @
bUUUU A
UB
UC
UD
UE
bUUUUUUUU F
#500000
b0000 *
0+
b0000 ;
0<
#4000000
1!
1)
1/
16
#6000000
1#
19
b0000 @
0B
0D
bUUUU0000 F
#8000000
0!
0)
0/
06
#10000000
0#
09
b0000 A
0C
#12000000
1!
1)
1/
16
#14000000
1#
bUUUU0000 ,
0-
19
bUUUU0000 =
0>
0E
b00000000 F
#16000000
0!
0)
0/
06
#18000000
0#
09
#20000000
1!
0"
b10101011 $
1%
1)
1/
00
b10101011 1
12
16
b10101011 7
18
0:
#22000000
1#
b00000000 ,
0.
19
b00000000 =
0?
#24000000
0!
b1010 '
1(
0)
0/
b1010 4
15
06
#24500000
b1010 *
1+
b1010 ;
1<
#26000000
0#
09
b1010 A
1C
#28000000
1!
b01010110 $
b1011 '
1)
1/
b01010110 1
b1011 4
16
b01010110 7
#28500000
b1011 *
b1011 ;
#30000000
1#
19
b1011 @
1B
1D
b10101011 F
#32000000
0!
b0101 '
0)
0/
b0101 4
06
#32500000
b0101 *
b0101 ;
#34000000
0#
09
b0101 A
#36000000
1!
b11101111 $
b0110 '
1)
1/
b11101111 1
b0110 4
16
b11101111 7
#36500000
b0110 *
b0110 ;
#38000000
1#
b10101011 ,
1-
19
b10101011 =
1>
b0110 @
b01010110 F
#40000000
0!
b1110 '
0)
0/
b1110 4
06
#40500000
b1110 *
b1110 ;
#42000000
0#
09
b1110 A
#44000000
1!
b10011000 $
b1111 '
1)
1/
b10011000 1
b1111 4
16
b10011000 7
#44500000
b1111 *
b1111 ;
#46000000
1#
b01010110 ,
19
b01010110 =
b1111 @
b11101111 F
#48000000
0!
b1001 '
0)
0/
b1001 4
06
#48500000
b1001 *
b1001 ;
#50000000
0#
09
b1001 A
#52000000
1!
0%
b1000 '
1)
1/
02
b1000 4
16
08
#52500000
b1000 *
b1000 ;
#54000000
1#
b11101111 ,
19
b11101111 =
b1000 @
b10011000 F
#56000000
0!
b1001 '
0(
0)
0/
b1001 4
05
06
#56500000
b1001 *
0+
b1001 ;
0<
#58000000
0#
09
0C
#60000000
1!
b1000 '
1)
1/
b1000 4
16
#60500000
b1000 *
b1000 ;
#62000000
1#
b10011000 ,
19
b10011000 =
0B
0D
#64000000
0!
b1001 '
0)
0/
b1001 4
06
#64500000
b1001 *
b1001 ;
#66000000
0#
09
#68000000
1!
b1000 '
1)
1/
b1000 4
16
#68500000
b1000 *
b1000 ;
#70000000
1#
0-
19
0>
#72000000
0!
b1001 '
0)
0/
b1001 4
06
#72500000
b1001 *
b1001 ;
#74000000
0#
09
#76000000
1!
b1000 '
1)
1/
b1000 4
16
#76500000
b1000 *
b1000 ;
#78000000
1#
19
#80000000
0!
b1001 '
0)
0/
b1001 4
06
#80500000
b1001 *
b1001 ;
#82000000
0#
09
#84000000
1!
b1000 '
1)
1/
b1000 4
16
#84500000
b1000 *
b1000 ;
#86000000
1#
19
#88000000
0!
b1001 '
0)
0/
b1001 4
06
#88500000
b1001 *
b1001 ;
#90000000
0#
09
#92000000
1!
b1000 '
1)
1/
b1000 4
16
#92500000
b1000 *
b1000 ;
#94000000
1#
19
#96000000
0!
b1001 '
0)
0/
b1001 4
06
#96500000
b1001 *
b1001 ;
#98000000
0#
09
#100000000
1!
b1000 '
1)
1/
b1000 4
16
#100500000
b1000 *
b1000 ;
#102000000
1#
19
#104000000
0!
b1001 '
0)
0/
b1001 4
06
#104500000
b1001 *
b1001 ;
#106000000
0#
09
#108000000
1!
b1000 '
1)
1/
b1000 4
16
#108500000
b1000 *
b1000 ;
#110000000
1#
19
#112000000
0!
b1001 '
0)
0/
b1001 4
06
#112500000
b1001 *
b1001 ;
#114000000
0#
09
#116000000
1!
b1000 '
1)
1/
b1000 4
16
#116500000
b1000 *
b1000 ;
#118000000
1#
19
#120000000
0!
b1001 '
0)
0/
b1001 4
06
#120500000
b1001 *
b1001 ;
#122000000
0#
09
#124000000
1!
b1000 '
1)
1/
b1000 4
16
#124500000
b1000 *
b1000 ;
#126000000
1#
19
#128000000
0!
b1001 '
0)
0/
b1001 4
06
#128500000
b1001 *
b1001 ;
#130000000
0#
09
#132000000
1!
b1000 '
1)
1/
b1000 4
16
#132500000
b1000 *
b1000 ;
#134000000
1#
19
#136000000
0!
b1001 '
0)
0/
b1001 4
06
#136500000
b1001 *
b1001 ;
#138000000
0#
09
#140000000
1!
b1000 '
1)
1/
b1000 4
16
#140500000
b1000 *
b1000 ;
#142000000
1#
19
#144000000
0!
b1001 '
0)
0/
b1001 4
06
#144500000
b1001 *
b1001 ;
#146000000
0#
09
#148000000
1!
b1000 '
1)
1/
b1000 4
16
#148500000
b1000 *
b1000 ;
